cloudmesh_slurm-4.3.3-py3.10-nspkg.pth
cloudmesh/slurm/__init__.py
cloudmesh/slurm/__version__.py
cloudmesh/slurm/slurm.py
cloudmesh/slurm/workflow.py
cloudmesh/slurm/command/__init__.py
cloudmesh/slurm/command/slurm.py
cloudmesh_slurm-4.3.3.dist-info/LICENSE
cloudmesh_slurm-4.3.3.dist-info/METADATA
cloudmesh_slurm-4.3.3.dist-info/WHEEL
cloudmesh_slurm-4.3.3.dist-info/namespace_packages.txt
cloudmesh_slurm-4.3.3.dist-info/top_level.txt
cloudmesh_slurm-4.3.3.dist-info/RECORD
